smia/__init__.py
smia/aas_model/__init__.py
smia/aas_model/aas_model_utils.py
smia/aas_model/extended_aas.py
smia/aas_model/extended_aas_model.py
smia/aas_model/extended_base.py
smia/aas_model/extended_concept_description.py
smia/aas_model/extended_submodel.py
smia/agents/__init__.py
smia/agents/extensible_smia_agent.py
smia/agents/smia_agent.py
smia/agents/smia_app_agent.py
smia/agents/smia_resource_agent.py
smia/assetconnection/__init__.py
smia/assetconnection/asset_connection.py
smia/assetconnection/http_asset_connection.py
smia/behaviours/__init__.py
smia/behaviours/aas_fsm_behaviour.py
smia/behaviours/acl_handling_behaviour.py
smia/behaviours/check_physical_asset_behaviour.py
smia/behaviours/end_behaviour.py
smia/behaviours/idle_behaviour.py
smia/behaviours/init_aas_archive_behaviour.py
smia/behaviours/init_aas_model_behaviour.py
smia/behaviours/negotiating_behaviour.py
smia/behaviours/specific_handle_behaviours/__init__.py
smia/behaviours/specific_handle_behaviours/handle_aas_related_svc_behaviour.py
smia/behaviours/specific_handle_behaviours/handle_capability_behaviour.py
smia/behaviours/specific_handle_behaviours/handle_negotiation_behaviour.py
smia/behaviours/specific_handle_behaviours/handle_svc_response_behaviour.py
smia/css_ontology/__init__.py
smia/css_ontology/capability_skill_module.py
smia/css_ontology/capability_skill_ontology.py
smia/css_ontology/css_ontology_utils.py
smia/css_ontology/css_operations.py
smia/launchers/__init__.py
smia/launchers/smia_cli_starter.py
smia/launchers/smia_docker_starter.py
smia/launchers/smia_starter.py
smia/logic/__init__.py
smia/logic/acl_smia_messages_utils.py
smia/logic/agent_services.py
smia/logic/exceptions.py
smia/logic/inter_smia_interactions_utils.py
smia/logic/negotiation_utils.py
smia/logic/services_utils.py
smia/states/__init__.py
smia/states/state_booting.py
smia/states/state_booting_resource.py
smia/states/state_idle.py
smia/states/state_running.py
smia/states/state_stopping.py
smia/utilities/__init__.py
smia-0.2.4.dist-info/licenses/LICENSE
smia-0.2.4.dist-info/METADATA
smia-0.2.4.dist-info/WHEEL
smia-0.2.4.dist-info/top_level.txt
smia-0.2.4.dist-info/RECORD
