Metadata-Version: 2.4
Name: smia
Version: 0.2.4
Summary: Self-configurable Manufacturing Industrial Agents (SMIA).
Author-email: Ekaitz Hurtado <ekaitz.hurtado@ehu.eus>
License: GNU Affero General Public License v3
Project-URL: Homepage, https://github.com/ekhurtado/SMIA
Project-URL: Documentation, https://smia.readthedocs.io/en/latest/
Project-URL: Repository, https://github.com/ekhurtado/SMIA
Project-URL: Issues, https://github.com/ekhurtado/SMIA/issues
Project-URL: Changelog, https://smia.readthedocs.io/en/latest/release_notes.html
Keywords: smia,dt,aas,i4.0,css
Classifier: Development Status :: 2 - Pre-Alpha
Classifier: Intended Audience :: Developers
Classifier: License :: OSI Approved :: GNU Affero General Public License v3
Classifier: Natural Language :: English
Classifier: Programming Language :: Python :: 3.10
Classifier: Programming Language :: Python :: 3.11
Classifier: Programming Language :: Python :: 3.12
Requires-Python: >=3.10
License-File: LICENSE
Requires-Dist: spade==3.3.3
Requires-Dist: basyx-python-sdk==1.2.0
Requires-Dist: owlready2==0.47
Requires-Dist: jsonpath-ng==1.7.0
Requires-Dist: aiohttp>=3.10.5
Requires-Dist: psutil~=6.1.0
Requires-Dist: jsonschema==4.22.0
Requires-Dist: tqdm~=4.67.1
Dynamic: license-file
